mkdocs_languagetool_plugin/__init__.py
mkdocs_languagetool_plugin/config.py
mkdocs_languagetool_plugin/docker.py
mkdocs_languagetool_plugin/languagetool.py
mkdocs_languagetool_plugin/plugin.py
mkdocs_languagetool_plugin/tasks.py
mkdocs_languagetool_plugin-0.1.0.dist-info/METADATA
mkdocs_languagetool_plugin-0.1.0.dist-info/WHEEL
mkdocs_languagetool_plugin-0.1.0.dist-info/entry_points.txt
mkdocs_languagetool_plugin-0.1.0.dist-info/top_level.txt
mkdocs_languagetool_plugin-0.1.0.dist-info/RECORD
