Metadata-Version: 2.2
Name: mkdocs-languagetool-plugin
Version: 0.1.0
Summary: Spellcheck your docs using a LanguageTool server
Home-page: https://github.com/six-two/mkdocs-placeholder-plugin
Author: six-two
Author-email: pip@six-two.dev
License: MIT License
Classifier: License :: OSI Approved :: MIT License
Classifier: Operating System :: POSIX :: Linux
Classifier: Programming Language :: Python :: 3
Classifier: Programming Language :: Python :: 3.9
Classifier: Programming Language :: Python :: 3.10
Classifier: Programming Language :: Python :: 3.11
Requires-Python: >=3.9
Requires-Dist: mkdocs>=1.4.0
